minimal_pba_cli_plugin_example/__init__.py
minimal_pba_cli_plugin_example/plugin.py
minimal_pba_cli_plugin_example-0.0.3.dist-info/METADATA
minimal_pba_cli_plugin_example-0.0.3.dist-info/WHEEL
minimal_pba_cli_plugin_example-0.0.3.dist-info/entry_points.txt
minimal_pba_cli_plugin_example-0.0.3.dist-info/top_level.txt
minimal_pba_cli_plugin_example-0.0.3.dist-info/RECORD
